ledoc_ui/__init__.py
ledoc_ui/static/index.css
ledoc_ui/static/index.html
ledoc_ui/static/index.js
ledoc_ui/static/leptonai.svg
ledoc_ui-0.1.0.dist-info/METADATA
ledoc_ui-0.1.0.dist-info/WHEEL
ledoc_ui-0.1.0.dist-info/top_level.txt
ledoc_ui-0.1.0.dist-info/RECORD
