Metadata-Version: 2.1
Name: ledoc-ui
Version: 0.1.0
Summary: A bundle of static files for ledoc as a python package.
License: MIT
